tokenizers_collection/__init__.py
tokenizers_collection/chinese_tokenizer_iterator.py
tokenizers_collection/cli.py
tokenizers_collection/config.py
tokenizers_collection/download_then_unzip.py
tokenizers_collection/helper.py
tokenizers_collection/tokenizers.py
tokenizers_collection-0.1.2.dist-info/DESCRIPTION.rst
tokenizers_collection-0.1.2.dist-info/METADATA
tokenizers_collection-0.1.2.dist-info/RECORD
tokenizers_collection-0.1.2.dist-info/WHEEL
tokenizers_collection-0.1.2.dist-info/entry_points.txt
tokenizers_collection-0.1.2.dist-info/metadata.json
tokenizers_collection-0.1.2.dist-info/top_level.txt
