Metadata-Version: 2.0
Name: tokenizers-collection
Version: 0.1.2
Summary: A simple iterator for using a set of Chinese tokenizer
Home-page: https://github.com/howl-anderson/tokenizers_collection
Author: Xiaoquan Kong
Author-email: u1mail2me@gmail.com
License: MIT license
Keywords: tokenizers_collection
Platform: UNKNOWN
Classifier: Development Status :: 2 - Pre-Alpha
Classifier: Intended Audience :: Developers
Classifier: License :: OSI Approved :: MIT License
Classifier: Natural Language :: English
Classifier: Programming Language :: Python :: 2
Classifier: Programming Language :: Python :: 2.7
Classifier: Programming Language :: Python :: 3
Classifier: Programming Language :: Python :: 3.4
Classifier: Programming Language :: Python :: 3.5
Classifier: Programming Language :: Python :: 3.6
Classifier: Programming Language :: Python :: 3.7
Requires-Dist: Click (>=6.0)
Requires-Dist: requests
Requires-Dist: jieba
Requires-Dist: thulac
Requires-Dist: pynlpir
Requires-Dist: pyltp
